pynsn/__init__.py
pynsn/_misc.py
pynsn/defaults.py
pynsn/exceptions.py
pynsn/fit.py
pynsn/geometry.py
pynsn/typing.py
pynsn/_shapes/__init__.py
pynsn/_shapes/abc_shapes.py
pynsn/_shapes/circ_shapes.py
pynsn/_shapes/colour.py
pynsn/_shapes/ellipse_geometry.py
pynsn/_shapes/shapes.py
pynsn/_stimulus/__init__.py
pynsn/_stimulus/convex_hull.py
pynsn/_stimulus/nsn_stimulus.py
pynsn/_stimulus/properties.py
pynsn/_stimulus/shape_array.py
pynsn/_stimulus/stimulus_colours.py
pynsn/_stimulus/stimulus_pair.py
pynsn/_stimulus/target_area.py
pynsn/collections/__init__.py
pynsn/collections/_abc_coll.py
pynsn/collections/_coll_stim.py
pynsn/collections/_coll_stim_pairs.py
pynsn/collections/fit.py
pynsn/image/__init__.py
pynsn/image/_base.py
pynsn/image/expyriment_stimulus.py
pynsn/image/pil_image.py
pynsn/image/pygame_surface.py
pynsn/image/svg_file.py
pynsn/plots/__init__.py
pynsn/plots/_collection_plots.py
pynsn/plots/_histograms.py
pynsn/rnd/__init__.py
pynsn/rnd/_distributions.py
pynsn/rnd/_distributions_2d.py
pynsn/rnd/_factory.py
pynsn/rnd/_random_shape.py
pynsn/rnd/_rng.py
pynsn-1.1.0.dist-info/LICENSE
pynsn-1.1.0.dist-info/WHEEL
pynsn-1.1.0.dist-info/METADATA
pynsn-1.1.0.dist-info/RECORD
