Metadata-Version: 2.3
Name: pynsn
Version: 1.1.0
Summary: Creating Non-Symbolic Number Displays
Author-email: Oliver Lindemann <lindemann@essb.eur.nl>
Requires-Python: >=3.10
Classifier: License :: OSI Approved :: MIT License
Requires-Dist: numpy>=2.1.3
Requires-Dist: pandas>=2.2
Requires-Dist: scipy>=1.14
Requires-Dist: matplotlib>=3.9
Requires-Dist: shapely>=2.0
Requires-Dist: svgwrite>=1.4
Requires-Dist: Pillow>=11.0
Requires-Dist: Sphinx>=5.1 ; extra == "doc"
Requires-Dist: sphinx-autodoc-typehints ; extra == "doc"
Requires-Dist: sphinx-rtd-theme ; extra == "doc"
Requires-Dist: pygame>=2.5 ; extra == "pygame"
Requires-Dist: pytest >=2.7.3 ; extra == "test"
Project-URL: Documentation, https://github.com/lindemann09/PyNSN
Project-URL: Source, https://github.com/lindemann09/PyNSN
Provides-Extra: doc
Provides-Extra: pygame
Provides-Extra: test
